code2flow/__init__.py
code2flow/__main__.py
code2flow/code_parser.py
code2flow/dot_code_generator.py
code2flow/example_1.py
code2flow/flowchart_generator.py
code2flow-1.0.1.dist-info/METADATA
code2flow-1.0.1.dist-info/WHEEL
code2flow-1.0.1.dist-info/entry_points.txt
code2flow-1.0.1.dist-info/top_level.txt
code2flow-1.0.1.dist-info/RECORD
