Metadata-Version: 2.1
Name: code2flow
Version: 1.0.1
Summary: A python project to allow generation of flow charts from a given code file.
Home-page: https://github.com/Dheeraj1998/code2flow
Author: Dheeraj Nair
Author-email: nair.dheeraj@yahoo.co.in
License: MIT
Platform: UNKNOWN
Classifier: License :: OSI Approved :: MIT License
Classifier: Programming Language :: Python :: 3.7
Requires-Dist: graphviz
